{
	"obstacles": [
		{
			"type": "wall",
			"hitbox": [ 0.5, 39 ],
			"color": 1566399999,
			"__color": "(comment) 1566399999 is 0xad6218ff",
			"position": [ 9, 0 ],
			"surface": "metal"
		},
		{
			"type": "wall",
			"hitbox": [ 0.5, 39 ],
			"color": 1566399999,
			"position": [ -9, 0 ],
			"surface": "metal"
		},
		{
			"type": "wall",
			"hitbox": [ 13, 0.5 ],
			"color": 1566399999,
			"position": [ -2.5, 19.25 ],
			"surface": "metal"

		},
		{
			"type": "wall",
			"hitbox": [ 3.8, 0.5 ],
			"color": 1566399999,
			"position": [ -7, -19.25 ],
			"surface": "metal"

		},
		{
			"type": "wall",
			"hitbox": [ 1, 0.5 ],
			"color": 1566399999,
			"position": [ 8.5, 19.25 ],
			"surface": "metal"

		},
		{
			"type": "wall",
			"hitbox": [ 3.8, 0.5 ],
			"color": 1566399999,
			"position": [ 7, -19.25 ],
			"surface": "metal"

		},
		{
			"type": "box",
			"position": [ -3, 11.5 ]
		},
		{
			"type": "box",
			"position": [ -5.2, 12 ]
		},
		{
			"type": "crate",
			"position": [ 0, -5 ],
			"special": "plus"
		},
		{
			"type": "stone",
			"position": [ 5, -9.5 ],
			"special": "pillar"
		},
		{
			"type": "stone",
			"position": [ -5, -9.5 ],
			"special": "pillar"
		}
	],
	"zones": [
		{
			"position": [ 0, 0 ],
			"hitbox": [ 18, 39.5 ],
			"map": true
		}
	],
	"mapColor": 1566399999,
	"floors": [
		{
			"type": "floor",
			"size": [ 18, 39.5 ],
			"position": [ 0, 0 ],
			"texture": {
				"path": "fixed/floor_warehouse.svg",
				"horizontalFill": 2
			}
		}
	],
	"roofs": [
		{
			"type": "roof",
			"hitbox": [ 19, 39.5 ],
			"position": [ 0, 0 ],
			"color": 1566399999,
			"texture": {
				"path": "fixed/roof_warehouse.svg"
			}
		}
	]
}